gns3_copilot/__init__.py
gns3_copilot/app.py
gns3_copilot/main.py
gns3_copilot/agent/__init__.py
gns3_copilot/agent/checkpoint_utils.py
gns3_copilot/agent/gns3_copilot.py
gns3_copilot/agent/model_factory.py
gns3_copilot/gns3_client/__init__.py
gns3_copilot/gns3_client/connector_factory.py
gns3_copilot/gns3_client/custom_gns3fy.py
gns3_copilot/gns3_client/gns3_create_drawing.py
gns3_copilot/gns3_client/gns3_delete_drawing.py
gns3_copilot/gns3_client/gns3_file_index.py
gns3_copilot/gns3_client/gns3_get_drawings.py
gns3_copilot/gns3_client/gns3_get_nodes.py
gns3_copilot/gns3_client/gns3_project_create.py
gns3_copilot/gns3_client/gns3_project_delete.py
gns3_copilot/gns3_client/gns3_project_list_files.py
gns3_copilot/gns3_client/gns3_project_lock.py
gns3_copilot/gns3_client/gns3_project_open.py
gns3_copilot/gns3_client/gns3_project_path.py
gns3_copilot/gns3_client/gns3_project_read_file.py
gns3_copilot/gns3_client/gns3_project_update.py
gns3_copilot/gns3_client/gns3_project_write_file.py
gns3_copilot/gns3_client/gns3_projects_list.py
gns3_copilot/gns3_client/gns3_topology_reader.py
gns3_copilot/gns3_client/gns3_update_drawing.py
gns3_copilot/log_config/__init__.py
gns3_copilot/log_config/logging_config.py
gns3_copilot/prompts/__init__.py
gns3_copilot/prompts/base_prompt.py
gns3_copilot/prompts/drawing_prompt.py
gns3_copilot/prompts/english_level_prompt_a1.py
gns3_copilot/prompts/english_level_prompt_a2.py
gns3_copilot/prompts/english_level_prompt_b1.py
gns3_copilot/prompts/english_level_prompt_b2.py
gns3_copilot/prompts/english_level_prompt_c1.py
gns3_copilot/prompts/english_level_prompt_c2.py
gns3_copilot/prompts/linux_specialist_prompt.py
gns3_copilot/prompts/notes_prompt.py
gns3_copilot/prompts/prompt_loader.py
gns3_copilot/prompts/title_prompt.py
gns3_copilot/prompts/vocie_prompt.py
gns3_copilot/prompts/voice_prompt_english_level_a1.py
gns3_copilot/prompts/voice_prompt_english_level_a2.py
gns3_copilot/prompts/voice_prompt_english_level_b1.py
gns3_copilot-0.3.0.dist-info/licenses/LICENSE
gns3_copilot-0.3.0.dist-info/METADATA
gns3_copilot-0.3.0.dist-info/WHEEL
gns3_copilot-0.3.0.dist-info/entry_points.txt
gns3_copilot-0.3.0.dist-info/top_level.txt
gns3_copilot-0.3.0.dist-info/RECORD
