Metadata-Version: 2.4
Name: gns3-copilot
Version: 0.3.0
Summary: AI-powered network automation assistant for GNS3
Author: Guobin Yue
Maintainer: Guobin Yue
License-Expression: MIT
Project-URL: Homepage, https://github.com/yueguobin/gns3-copilot
Project-URL: Repository, https://github.com/yueguobin/gns3-copilot
Project-URL: Documentation, https://yueguobin.github.io/gns3-copilot/
Project-URL: Bug Reports, https://github.com/yueguobin/gns3-copilot/issues
Keywords: gns3,network-automation,ai,langchain,nornir,netmiko,networking,automation,copilot
Classifier: Development Status :: 4 - Beta
Classifier: Intended Audience :: Developers
Classifier: Intended Audience :: System Administrators
Classifier: Intended Audience :: Information Technology
Classifier: Topic :: System :: Networking
Classifier: Topic :: Software Development :: Libraries :: Python Modules
Classifier: Programming Language :: Python :: 3
Classifier: Programming Language :: Python :: 3.10
Classifier: Programming Language :: Python :: 3.11
Classifier: Programming Language :: Python :: 3.12
Classifier: Programming Language :: Python :: 3.13
Classifier: Operating System :: OS Independent
Requires-Python: >=3.10
License-File: LICENSE
Requires-Dist: langchain>=1.2.0
Requires-Dist: langchain-core>=1.2.6
Requires-Dist: langgraph>=1.0.5
Requires-Dist: langgraph-cli>=0.4.11
Requires-Dist: langgraph-cli[inmem]>=0.4.11
Requires-Dist: langgraph-checkpoint-sqlite>=3.0.1
Requires-Dist: langchain-openai>=1.1.6
Requires-Dist: langchain-anthropic>=1.3.1
Requires-Dist: langchain-google-genai>=4.1.3
Requires-Dist: langchain-aws>=1.2.0
Requires-Dist: langchain-ollama>=1.0.1
Requires-Dist: langchain-deepseek>=1.0.1
Requires-Dist: langchain-xai>=1.2.1
Requires-Dist: netmiko>=4.6.0
Requires-Dist: nornir>=3.5.0
Requires-Dist: nornir-netmiko>=1.0.1
Requires-Dist: nornir-utils>=0.2.0
Requires-Dist: nornir-salt>=0.23.0
Requires-Dist: python-dotenv>=1.2.1
Requires-Dist: requests>=2.32.5
Requires-Dist: urllib3>=2.6.2
Requires-Dist: pydantic>=2.12.5
Requires-Dist: PyJWT>=2.10.1
Requires-Dist: typing-extensions>=4.15.0
Requires-Dist: telnetlib3>=2.0.8
Requires-Dist: streamlit>=1.52.2
Requires-Dist: soundfile>=0.13.1
Provides-Extra: dev
Requires-Dist: pytest>=6.0; extra == "dev"
Requires-Dist: pytest-cov>=2.0; extra == "dev"
Requires-Dist: black>=21.0; extra == "dev"
Requires-Dist: flake8>=3.8; extra == "dev"
Requires-Dist: mypy>=0.800; extra == "dev"
Requires-Dist: ruff>=0.1.0; extra == "dev"
Requires-Dist: bandit>=1.7.0; extra == "dev"
Requires-Dist: safety>=2.0.0; extra == "dev"
Provides-Extra: docs
Requires-Dist: mkdocs>=1.6.0; extra == "docs"
Requires-Dist: mkdocs-material>=9.5.0; extra == "docs"
Requires-Dist: mkdocs-material-extensions>=1.3.0; extra == "docs"
Dynamic: license-file
